reado/__init__.py
reado/main.py
Reado-0.1.dist-info/LICENSE
Reado-0.1.dist-info/METADATA
Reado-0.1.dist-info/WHEEL
Reado-0.1.dist-info/entry_points.txt
Reado-0.1.dist-info/top_level.txt
Reado-0.1.dist-info/RECORD
