Metadata-Version: 2.1
Name: Reado
Version: 0.1
Summary: A CLI tool to generate README files based on project structure and configuration
Home-page: https://github.com/pezhvak98/Reado
Author: Pezhvak
Author-email: m.8562.m@gmail.com
License: MIT
Project-URL: Bug Reports, https://github.com/pezhvak98/Reado/issues
Project-URL: Source, https://github.com/pezhvak98/Reado
Keywords: CLI,project-structure,readme-generator
Classifier: Development Status :: 5 - Production/Stable
Classifier: Environment :: Console
Classifier: Intended Audience :: Developers
Classifier: License :: OSI Approved :: MIT License
Classifier: Programming Language :: Python :: 3
Classifier: Programming Language :: Python :: 3.7
Classifier: Programming Language :: Python :: 3.8
Classifier: Programming Language :: Python :: 3.9
Classifier: Programming Language :: Python :: 3.10
Classifier: Programming Language :: Python :: 3.12
Classifier: Topic :: Software Development :: Libraries :: Python Modules
Classifier: Topic :: Utilities
Requires-Python: >=3.6
License-File: LICENSE
Requires-Dist: requests
Requires-Dist: nimblex
